kra/__init__.py
kra/columns.py
kra/label.py
kra/polars_api.py
kra/process.py
kra/utils.py
kra-0.1.0.dist-info/licenses/LICENSE
kra-0.1.0.dist-info/METADATA
kra-0.1.0.dist-info/WHEEL
kra-0.1.0.dist-info/top_level.txt
kra-0.1.0.dist-info/RECORD
