Metadata-Version: 2.4
Name: kra
Version: 0.1.0
Summary: Convenient DataFrame column operations for Polars.
Author: Krzysztof Joachimiak
License-Expression: MIT
Project-URL: Homepage, https://github.com/krzjoa/kra
Project-URL: Documentation, https://kra.readthedocs.io/
Requires-Python: >=3.7
License-File: LICENSE
Requires-Dist: polars>=0.16.0
Dynamic: license-file
